an_website/__init__.py
an_website/__main__.py
an_website/ca-bundle.crt
an_website/main.py
an_website/py.typed
an_website/screenfetch
an_website/backdoor/__init__.py
an_website/backdoor/backdoor.py
an_website/backdoor/backdoor_client.py
an_website/contact/__init__.py
an_website/contact/contact.py
an_website/currency_converter/__init__.py
an_website/currency_converter/converter.js
an_website/currency_converter/converter.py
an_website/discord/__init__.py
an_website/discord/discord.py
an_website/elasticsearch/component_templates/ecs/LICENSE.txt
an_website/elasticsearch/component_templates/ecs/NOTICE.txt
an_website/elasticsearch/component_templates/ecs/agent.json
an_website/elasticsearch/component_templates/ecs/base.json
an_website/elasticsearch/component_templates/ecs/client.json
an_website/elasticsearch/component_templates/ecs/cloud.json
an_website/elasticsearch/component_templates/ecs/container.json
an_website/elasticsearch/component_templates/ecs/data_stream.json
an_website/elasticsearch/component_templates/ecs/destination.json
an_website/elasticsearch/component_templates/ecs/dll.json
an_website/elasticsearch/component_templates/ecs/dns.json
an_website/elasticsearch/component_templates/ecs/ecs.json
an_website/elasticsearch/component_templates/ecs/email.json
an_website/elasticsearch/component_templates/ecs/error.json
an_website/elasticsearch/component_templates/ecs/event.json
an_website/elasticsearch/component_templates/ecs/file.json
an_website/elasticsearch/component_templates/ecs/group.json
an_website/elasticsearch/component_templates/ecs/host.json
an_website/elasticsearch/component_templates/ecs/http.json
an_website/elasticsearch/component_templates/ecs/log.json
an_website/elasticsearch/component_templates/ecs/network.json
an_website/elasticsearch/component_templates/ecs/observer.json
an_website/elasticsearch/component_templates/ecs/orchestrator.json
an_website/elasticsearch/component_templates/ecs/organization.json
an_website-22.7.14.dist-info/LICENSE.md
an_website-22.7.14.dist-info/METADATA
an_website-22.7.14.dist-info/WHEEL
an_website-22.7.14.dist-info/top_level.txt
an_website-22.7.14.dist-info/RECORD
