Metadata-Version: 2.1
Name: an-website
Version: 22.7.14
Summary: #1 Website in the Worlds
Home-page: https://github.com/asozialesnetzwerk/an-website
Author: Das Asoziale Netzwerk
Author-email: contact@asozial.org
License: AGPLv3+
Platform: OS Independent
Classifier: Development Status :: 5 - Production/Stable
Classifier: License :: OSI Approved :: GNU Affero General Public License v3 or later (AGPLv3+)
Classifier: Operating System :: OS Independent
Classifier: Programming Language :: Python
Classifier: Programming Language :: Python :: 3
Classifier: Programming Language :: Python :: 3 :: Only
Classifier: Programming Language :: Python :: 3.10
Classifier: Programming Language :: Python :: 3.11
Classifier: Programming Language :: Python :: 3.12
Classifier: Programming Language :: Python :: Implementation :: CPython
Classifier: Typing :: Typed
Requires-Python: >=3.10
License-File: LICENSE.md
Requires-Dist: accept-types (==0.4.1)
Requires-Dist: aiodns (==3.0.0)
Requires-Dist: aiohttp[speedups] (==3.8.1)
Requires-Dist: aiosignal (==1.2.0)
Requires-Dist: ansi2html (==1.8.0)
Requires-Dist: async-timeout (==4.0.2)
Requires-Dist: attrs (==21.4.0)
Requires-Dist: beautifulsoup4 (==4.11.1)
Requires-Dist: blake3 (==0.3.1)
Requires-Dist: brotli (==1.0.9)
Requires-Dist: cchardet (==2.1.7)
Requires-Dist: certifi (==2022.6.15)
Requires-Dist: cffi (==1.15.1)
Requires-Dist: charset-normalizer (==2.1.0)
Requires-Dist: colorama (==0.4.5)
Requires-Dist: cython (==0.29.30)
Requires-Dist: defusedxml (==0.7.1)
Requires-Dist: deprecated (==1.2.13)
Requires-Dist: dill (==0.3.5.1)
Requires-Dist: dunamai (==1.12.0)
Requires-Dist: ecs-logging (==1.1.0)
Requires-Dist: elastic-apm (==6.10.1)
Requires-Dist: elastic-enterprise-search (==7.17.0)
Requires-Dist: elastic-transport (==7.16.0)
Requires-Dist: elasticsearch[async] (==7.17.4)
Requires-Dist: emoji (==1.7.0)
Requires-Dist: frozendict (==2.3.2)
Requires-Dist: frozenlist (==1.3.0)
Requires-Dist: funcparserlib (==1.0.0)
Requires-Dist: get-version (==3.5.4)
Requires-Dist: hiredis (==2.0.0)
Requires-Dist: html2text (==2020.1.16)
Requires-Dist: hy (==0.24.0)
Requires-Dist: hyrule (==0.2)
Requires-Dist: idna (==3.3)
Requires-Dist: jxlpy (==0.9.1)
Requires-Dist: lxml (==4.9.1)
Requires-Dist: mpmath (==1.2.1)
Requires-Dist: multidict (==6.0.2)
Requires-Dist: namedthreads (==1.0)
Requires-Dist: numpy (==1.23.1)
Requires-Dist: orjson (==3.7.7)
Requires-Dist: packaging (==21.3)
Requires-Dist: pillow (==9.2.0)
Requires-Dist: pycares (==4.2.1)
Requires-Dist: pycparser (==2.21)
Requires-Dist: pycryptodome (==3.15.0)
Requires-Dist: pycurl (==7.45.1)
Requires-Dist: pyjwt (==2.4.0)
Requires-Dist: pyparsing (==3.0.9)
Requires-Dist: python-dateutil (==2.8.2)
Requires-Dist: python-levenshtein (==0.12.2)
Requires-Dist: pyyaml (==6.0)
Requires-Dist: redis[hiredis] (==4.3.4)
Requires-Dist: setuptools (==63.1.0)
Requires-Dist: six (==1.16.0)
Requires-Dist: soupsieve (==2.3.2.post1)
Requires-Dist: sympy (==1.10.1)
Requires-Dist: tornado (==6.2)
Requires-Dist: tzdata (==2022.1)
Requires-Dist: ultradict (==0.0.4)
Requires-Dist: urllib3 (==1.26.10)
Requires-Dist: uvloop (==0.16.0)
Requires-Dist: wrapt (==1.14.1)
Requires-Dist: yarl (==1.7.2)
